.gitignore
.travis.yml
LICENSE
README.md
package.sh
setup.cfg
setup.py
cnctcli/__init__.py
cnctcli/ccli.py
cnctcli/config.py
cnctcli/actions/__init__.py
cnctcli/actions/products.py
cnctcli/commands/__init__.py
cnctcli/commands/product.py
product_sync.egg-info/PKG-INFO
product_sync.egg-info/SOURCES.txt
product_sync.egg-info/dependency_links.txt
product_sync.egg-info/entry_points.txt
product_sync.egg-info/requires.txt
product_sync.egg-info/top_level.txt
product_sync.egg-info/zip-safe
requirements/dev.txt
resources/ccli.spec
resources/config.json