Metadata-Version: 2.1
Name: product-sync
Version: 1.5
Summary: CloudBlue Connect Product Synchronizer CLI
Home-page: https://connect.cloudblue.com
Author: CloudBlue
License: UNKNOWN
Keywords: fulfillment products synchronizer vendor connect cloudblue
Platform: UNKNOWN
Classifier: Development Status :: 5 - Production/Stable
Classifier: Environment :: Console
Classifier: Operating System :: POSIX :: Linux
Classifier: Programming Language :: Python :: 3.6
Classifier: Programming Language :: Python :: 3.7
Classifier: Programming Language :: Python :: 3.8
Classifier: Topic :: Utilities
Requires-Python: >=3.6
